api_linter_101-1.1.0.data/scripts/linting
linter/__init__.py
linter/array_name_funcs.py
linter/generic_funcs.py
linter/internal_ref_funcs.py
linter/key_name_funcs.py
linter/key_value_funcs.py
linter/linter.py
linter/logger.py
linter/object_example_funcs.py
linter/required_path_funcs.py
linter/utils.py
linter/yaml_property_funcs.py
api_linter_101-1.1.0.dist-info/METADATA
api_linter_101-1.1.0.dist-info/WHEEL
api_linter_101-1.1.0.dist-info/top_level.txt
api_linter_101-1.1.0.dist-info/RECORD
